burgissApiWrapper/__init__.py
burgissApiWrapper/burgissApi.py
burgissApiWrapper/py.typed
burgiss_api-0.0.7.dist-info/METADATA
burgiss_api-0.0.7.dist-info/WHEEL
burgiss_api-0.0.7.dist-info/top_level.txt
burgiss_api-0.0.7.dist-info/RECORD
