Metadata-Version: 2.1
Name: burgiss-api
Version: 0.0.7
Summary: An api wrapper package for financial data provided by Burgiss
Home-page: UNKNOWN
Author: Jared Fallt
Author-email: fallt.jared@gmail.com
License: MIT
Platform: UNKNOWN
Classifier: Development Status :: 3 - Alpha
Classifier: Intended Audience :: Developers
Classifier: License :: OSI Approved :: MIT License
Classifier: Programming Language :: Python :: 3
Requires-Dist: atomicwrites (>=1.4.0)
Requires-Dist: attrs (>=21.2.0)
Requires-Dist: certifi (>=2021.5.30)
Requires-Dist: cffi (>=1.14.6)
Requires-Dist: charset-normalizer (>=2.0.4)
Requires-Dist: colorama (>=0.4.4)
Requires-Dist: cryptography (>=3.4.8)
Requires-Dist: idna (>=3.2)
Requires-Dist: iniconfig (>=1.1.1)
Requires-Dist: numpy (>=1.21.2)
Requires-Dist: packaging (>=21.0)
Requires-Dist: pandas (>=1.3.3)
Requires-Dist: pluggy (>=1.0.0)
Requires-Dist: py (>=1.10.0)
Requires-Dist: pycparser (>=2.20)
Requires-Dist: PyJWT (>=2.1.0)
Requires-Dist: pyodbc (>=4.0.32)
Requires-Dist: pyOpenSSL (>=20.0.1)
Requires-Dist: pyparsing (>=2.4.7)
Requires-Dist: python-dateutil (>=2.8.2)
Requires-Dist: pytz (>=2021.1)
Requires-Dist: requests (>=2.26.0)
Requires-Dist: six (>=1.16.0)
Requires-Dist: toml (>=0.10.2)
Requires-Dist: urllib3 (>=1.26.6)
Provides-Extra: testing
Requires-Dist: pytest (>=6.2.5) ; extra == 'testing'
Requires-Dist: pytest-cov (>=3.0.0) ; extra == 'testing'
Requires-Dist: mypy (>=0.910) ; extra == 'testing'
Requires-Dist: flake (>=4.0.1) ; extra == 'testing'
Requires-Dist: tox (>=3.24.4) ; extra == 'testing'
